gdtm/__init__.py
gdtm/helpers/__init__.py
gdtm/helpers/common.py
gdtm/helpers/exceptions.py
gdtm/helpers/weighting.py
gdtm/models/__init__.py
gdtm/models/cstb.py
gdtm/models/denlda.py
gdtm/models/detnd.py
gdtm/models/dnlda.py
gdtm/models/dtnd.py
gdtm/models/enlda.py
gdtm/models/etnd.py
gdtm/models/gtm.py
gdtm/models/nlda.py
gdtm/models/tnd.py
gdtm/wrappers/__init__.py
gdtm/wrappers/base_wrapper.py
gdtm/wrappers/dlda.py
gdtm/wrappers/dtnd.py
gdtm/wrappers/gtm.py
gdtm/wrappers/lda.py
gdtm/wrappers/tnd.py
gdtm-1.0.3.dist-info/LICENSE
gdtm-1.0.3.dist-info/METADATA
gdtm-1.0.3.dist-info/WHEEL
gdtm-1.0.3.dist-info/top_level.txt
gdtm-1.0.3.dist-info/RECORD
