Metadata-Version: 2.1
Name: gdtm
Version: 1.0.3
Summary: A Topic Modeling Package
Home-page: https://github.com/pypa/gdtm
Author: Rob Churchill
Author-email: rjc111@georgetown.com
License: UNKNOWN
Project-URL: Bug Tracker, https://github.com/pypa/gdtm/issues
Platform: UNKNOWN
Classifier: Programming Language :: Python :: 3
Classifier: License :: OSI Approved :: MIT License
Classifier: Operating System :: OS Independent
Requires-Python: >=3.6
License-File: LICENSE
Requires-Dist: gensim (>=4.0)
